pywalletscan/__init__.py
pywalletscan/api.py
pywalletscan-0.0.8.dist-info/LICENSE
pywalletscan-0.0.8.dist-info/METADATA
pywalletscan-0.0.8.dist-info/WHEEL
pywalletscan-0.0.8.dist-info/top_level.txt
pywalletscan-0.0.8.dist-info/RECORD
