Metadata-Version: 2.1
Name: pywalletscan
Version: 0.0.8
Summary: A Python Wrapper Implementation of Etherscan
Home-page: https://github.com/efssisbdyy/pywalletscan
License: MIT
Keywords: ETH,Etherium,Bitcoin,wallet,Etherscan
Classifier: Development Status :: 2 - Pre-Alpha
Classifier: License :: OSI Approved :: MIT License
Classifier: Programming Language :: Python :: 3
License-File: LICENSE
